setup.py
sutui/__init__.py
sutui/sutui.py
sutui.egg-info/PKG-INFO
sutui.egg-info/SOURCES.txt
sutui.egg-info/dependency_links.txt
sutui.egg-info/top_level.txt