Metadata-Version: 1.0
Name: sutui
Version: 0.3
Summary: Sutui Python SDK
Home-page: https://github.com/jeffkit/sutui
Author: jeff kit
Author-email: bbmyth@gmail.com
License: UNKNOWN
Platform: UNKNOWN
